<?xml version="1.0" encoding="UTF-8"?>
<!DOCTYPE suite SYSTEM "http://testng.org/testng-1.0.dtd">
<suite name="SuiteQA" allow-return-values="true" parallel="false" verbose="1" thread-count="2">

	<listeners>
		<listener class-name="com.elliemae.core.Reporter.CustomReporter" />
		<listener class-name="com.elliemae.core.listener.RetryListener"/>
		<listener class-name="com.elliemae.core.listener.PostTestListener"/>
	</listeners>

	<parameter name="environmentName" value="QA1"></parameter>
	<parameter name="environmentUserName" value=""></parameter>
	<parameter name="environmentPassword" value=""></parameter>
	<parameter name="environmentClientID" value="BE11170520"></parameter>
	<parameter name="jenkinsJobName" value=""></parameter>
	<parameter name="updateTestStatusToJIRA" value="no"></parameter>
	<parameter name="jiraProjectName" value="EMATF"></parameter>	
	<parameter name="testCycleVersion" value="ATF 2.3"></parameter>	

	
	<test name="APIDemoTest">
		<parameter name="platform" value="API"/>
		<classes>			
			<class name="com.elliemae.testcases.maintenance.Resetecsautopass">	
				<methods>
					<include name="resetPassword"></include>
				</methods>				
			</class>						
		</classes>
	</test>
		
</suite>